patkit/__init__.py
patkit/cli.py
patkit/cli_commands.py
patkit/computational.py
patkit/constants.py
patkit/data_loader.py
patkit/data_processor.py
patkit/errors.py
patkit/get_modality_types.py
patkit/initialise.py
patkit/interpolate_raw_uti.py
patkit/interpreter.py
patkit/patgrid.py
patkit/qt_annotator.py
patkit/ui_callbacks.py
patkit/annotations/__init__.py
patkit/annotations/peaks.py
patkit/audio_processing/__init__.py
patkit/audio_processing/audio_processing.py
patkit/configuration/__init__.py
patkit/configuration/configuration.py
patkit/configuration/configuration_models.py
patkit/configuration/configuration_parsers.py
patkit/configuration/exclusion_list_functions.py
patkit/data_import/AAA_raw_ultrasound.py
patkit/data_import/AAA_recordings.py
patkit/data_import/AAA_splines.py
patkit/data_import/RASL_3D_ultrasound_recordings.py
patkit/data_import/__init__.py
patkit/data_import/audio.py
patkit/data_import/session_import_config.py
patkit/data_import/spline_import_config.py
patkit/data_import/three_dim_ultrasound.py
patkit/data_import/video.py
patkit/data_import/wav_recordings.py
patkit/data_structures/__init__.py
patkit/data_structures/base_classes.py
patkit/data_structures/data_structures.py
patkit/data_structures/metadata_classes.py
patkit/default_configuration/patkit-data.yaml
patkit/default_configuration/patkit-gui.yaml
patkit/default_configuration/patkit-publish.yaml
patkit/default_configuration/patkit_logging_configuration.json
patkit/export/__init__.py
patkit/export/images.py
patkit/export/metadata.py
patkit/export/modality_data.py
patkit/external_class_extensions/__init__.py
patkit/external_class_extensions/base_model_extensions.py
patkit/external_class_extensions/enum_extensions.py
patkit/gui/__init__.py
patkit/gui/annotator_window.py
patkit/gui/boundary_animation.py
patkit/gui/dialog_template.py
patkit/gui/image_save_dialog.py
patkit/gui/list_save_dialog.py
patkit/gui/ofbrowse.py
patkit/gui/replace_dialog.py
patkit/import_formats/__init__.py
patkit-0.19.0.dist-info/METADATA
patkit-0.19.0.dist-info/WHEEL
patkit-0.19.0.dist-info/entry_points.txt
patkit-0.19.0.dist-info/licenses/LICENSE.markdown
patkit-0.19.0.dist-info/RECORD
