Metadata-Version: 2.4
Name: patkit
Version: 0.19.0
Summary: Phonetic Analysis ToolKit: Tools for processing phonetic data
Project-URL: bug_tracker, https://github.com/giuthas/patkit/issues
Project-URL: changelog, https://github.com/giuthas/patkit/blob/main/docs/Release_notes.markdown
Project-URL: documentation, https://giuthas.github.io/patkit/
Project-URL: homepage, https://github.com/giuthas/patkit/
Project-URL: repository, https://github.com/giuthas/patkit/
Author: Pertti Palo, Scott Moisik, Matthew Faytak, Motoki Saito
Author-email: giuthas@gmail.com
Maintainer-email: Pertti Palo <giuthas@gmail.com>
License: ### GNU GENERAL PUBLIC LICENSE
License-File: LICENSE.markdown
Keywords: articulation,phonetics,speech,splines,textgrid,ultrasound
Classifier: Development Status :: 3 - Alpha
Classifier: Programming Language :: Python
Requires-Python: >=3.10.13
Requires-Dist: build>=1.2.2.post1
Requires-Dist: click-default-group>=1.2.4
Requires-Dist: click>=8.1.8
Requires-Dist: dipy>=1.10.0
Requires-Dist: icecream>=2.1.3
Requires-Dist: licenseheaders>=0.8.8
Requires-Dist: matplotlib>=3.10.0
Requires-Dist: more-itertools>=10.5.0
Requires-Dist: mpl-point-clicker>=0.4.1
Requires-Dist: nestedtext>=3.7
Requires-Dist: numpy>=2.2.1
Requires-Dist: pdoc>=15.0.1
Requires-Dist: praat-textgrids>=1.4.0
Requires-Dist: pydantic>=2.10.4
Requires-Dist: pydicom>=3.0.1
Requires-Dist: pylint>=3.3.3
Requires-Dist: pyqt6>=6.8.0
Requires-Dist: pyreadline3>=3.5.4; platform_system == 'Windows'
Requires-Dist: qbstyles>=0.1.4
Requires-Dist: scipy>=1.15.0
Requires-Dist: seaborn>=0.13.2
Requires-Dist: setuptools>=75.7.0
Requires-Dist: sk-video>=1.1.10
Requires-Dist: strictyaml>=1.7.3
Requires-Dist: virtualenv>=20.28.1
